{
"type": "FeatureCollection",
"name": "file89232b1c911",
"crs": { "type": "name", "properties": { "name": "urn:ogc:def:crs:OGC:1.3:CRS84" } },
"features": [
{ "type": "Feature", "properties": { "floodAreaID": "054WATBT1" }, "geometry": { "type": "Point", "coordinates": [ 1.566239616782151, 52.699129601069956 ] } },
{ "type": "Feature", "properties": { "floodAreaID": "122WAF949" }, "geometry": { "type": "Point", "coordinates": [ -0.65664664376436, 54.188810479668184 ] } },
{ "type": "Feature", "properties": { "floodAreaID": "054WATBT3" }, "geometry": { "type": "Point", "coordinates": [ 1.619769681559488, 52.488144784606277 ] } },
{ "type": "Feature", "properties": { "floodAreaID": "054WATBT2" }, "geometry": { "type": "Point", "coordinates": [ 1.578573916370916, 52.584052090625534 ] } },
{ "type": "Feature", "properties": { "floodAreaID": "065WAC404" }, "geometry": { "type": "Point", "coordinates": [ -0.566964446640404, 50.801600003603745 ] } },
{ "type": "Feature", "properties": { "floodAreaID": "054WAFNF2" }, "geometry": { "type": "Point", "coordinates": [ 1.276659547147595, 52.790394267570221 ] } },
{ "type": "Feature", "properties": { "floodAreaID": "122WAF950" }, "geometry": { "type": "Point", "coordinates": [ -0.893961308185669, 53.846686264426971 ] } }
]
}
