{
"type": "FeatureCollection",
"name": "file88b30bf84a6",
"crs": { "type": "name", "properties": { "name": "urn:ogc:def:crs:OGC:1.3:CRS84" } },
"features": [
{ "type": "Feature", "properties": { "floodAreaID": "054WATBT1" }, "geometry": { "type": "Point", "coordinates": [ 1.566239616782151, 52.699129601069956 ] } }
]
}
